mpimpy/__init__.py
mpimpy/memmat.py
mpimpy/memmatdp.py
mpimpy/memmatfp.py
mpimpy/crossbar/__init__.py
mpimpy/crossbar/crossbar.py
mpimpy-1.0.dist-info/licenses/LICENSE.txt
mpimpy-1.0.dist-info/METADATA
mpimpy-1.0.dist-info/WHEEL
mpimpy-1.0.dist-info/top_level.txt
mpimpy-1.0.dist-info/RECORD
