Metadata-Version: 2.4
Name: mpimpy
Version: 1.0
Summary: A python algorithm-hardware co-design framework for memristor-based in-memory computing.
Home-page: https://github.com/lanceyang694
Author: Ling Yang
Author-email: 3299285328@qq.com
Maintainer: Researchers from Prof. Yi Li's group at HUST
License: MIT
Requires-Python: >=3.6
License-File: LICENSE.txt
Requires-Dist: numpy
Requires-Dist: scipy
Requires-Dist: matplotlib
Requires-Dist: pandas
Dynamic: author
Dynamic: author-email
Dynamic: description
Dynamic: description-content-type
Dynamic: home-page
Dynamic: license
Dynamic: license-file
Dynamic: maintainer
Dynamic: requires-dist
Dynamic: requires-python
Dynamic: summary
